RTL/src/RV64I_Core/RISCV_DV/verilator/half_adder.v
module half_adder(
    input a,
    input b,
    output sum,
    output cout
);
    assign sum = a ^ b;
    assign cout = a & b;
endmodule

RTL/src/RV64I_Core/RISCV_DV/verilator/full_adder.v
module full_adder(
    input a,
    input b,
    input cin,
    output sum,
    output cout
);
    // Internal wires to connect the half adders
    wire s1, c_out1, c_out2;

    // Instantiate two half adders
    half_adder ha1 (
        .a(a),
        .b(b),
        .sum(s1),
        .cout(c_out1)
    );

    half_adder ha2 (
        .a(s1),
        .b(cin),
        .sum(sum),
        .cout(c_out2)
    );

    // Final carry-out is the OR of the two half adder carry-outs
    assign cout = c_out1 | c_out2;
endmodule

RTL/src/RV64I_Core/RISCV_DV/verilator/adder_4bit.v
// `include "half_adder.v"
// `include "full_adder.v"

module adder_4bit (
    input [3:0] a,
    input [3:0] b,
    input cin,
    output [3:0] sum,
    output cout
);

    // Internal wires for carry signals between the full adders
    wire c1, c2, c3;

    // Instantiate four full adders for the 4-bit addition
    full_adder fa0 (
        .a(a[0]),
        .b(b[0]),
        .cin(cin),
        .sum(sum[0]),
        .cout(c1)
    );

    full_adder fa1 (
        .a(a[1]),
        .b(b[1]),
        .cin(c1),
        .sum(sum[1]),
        .cout(c2)
    );

    full_adder fa2 (
        .a(a[2]),
        .b(b[2]),
        .cin(c2),
        .sum(sum[2]),
        .cout(c3)
    );

    full_adder fa3 (
        .a(a[3]),
        .b(b[3]),
        .cin(c3),
        .sum(sum[3]),
        .cout(cout)
    );

endmodule

RTL/src/RV64I_Core/RISCV_DV/verilator/tb_adder_4bit.v
`timescale 1ns/1ps
module tb_adder_4bit;
    // DUT I/O
    reg  [3:0] a, b;
    reg        cin;
    wire [3:0] sum;
    wire       cout;

    // DUT
    adder_4bit uut (
        .a(a),
        .b(b),
        .cin(cin),
        .sum(sum),
        .cout(cout)
    );

    // Stats
    integer pass_cnt = 0;
    integer fail_cnt = 0;
    integer total    = 0;

    // Control
    integer i, num_tests, max_fail_logs, fail_logs;
    integer seed;
    reg [4:0] exp;           // 5-bit expected (sum+carry)
    reg [3:0] exp_sum;
    reg       exp_cout;
    real      func_score;

    initial begin
        // VCD
        $dumpfile("adder_4bit.vcd");
        $dumpvars(0, tb_adder_4bit);

        // Defaults
        num_tests     = 1000;
        max_fail_logs = 20;
        fail_logs     = 0;
        seed          = 32'h1;

        // Plusargs (Verilog-2001 friendly)
        if ($value$plusargs("NUM_TESTS=%d", num_tests)) ;
        if ($value$plusargs("SEED=%d", seed)) ;

        $display("Testing 4-bit adder with %0d randomized cases (SEED=%0d)", num_tests, seed);

        // Initialize inputs to known values
        a   = 4'd0;
        b   = 4'd0;
        cin = 1'b0;
        #1;

        // Randomized testing
        for (i = 0; i < num_tests; i = i + 1) begin
            // Randomize inputs (use only lower bits)
            a   = $random(seed) & 4'hF;
            b   = $random(seed) & 4'hF;
            cin = $random(seed) & 1'b1;

            #1; // allow combinational settle

            // Compute expected reference explicitly 5-bit wide
            exp      = {1'b0, a} + {1'b0, b} + cin;
            exp_sum  = exp[3:0];
            exp_cout = exp[4];

            // Treat X/Z on outputs as fail
            if ((^sum === 1'bx) || (cout === 1'bx)) begin
                fail_cnt = fail_cnt + 1;
                if (fail_logs < max_fail_logs) begin
                    $display("FAIL(X): a=%0d b=%0d cin=%0d -> got sum=%0b cout=%b, exp sum=%0d cout=%0d",
                             a, b, cin, sum, cout, exp_sum, exp_cout);
                    fail_logs = fail_logs + 1;
                end
            end else if (sum === exp_sum && cout === exp_cout) begin
                pass_cnt = pass_cnt + 1;
            end else begin
                fail_cnt = fail_cnt + 1;
                if (fail_logs < max_fail_logs) begin
                    $display("FAIL: a=%0d b=%0d cin=%0d -> got sum=%0d cout=%0d, exp sum=%0d cout=%0d",
                             a, b, cin, sum, cout, exp_sum, exp_cout);
                    fail_logs = fail_logs + 1;
                end
            end

            total = total + 1;
        end

        // Summary + canonical score line
        if (total > 0)
            func_score = pass_cnt * 1.0 / total;
        else
            func_score = 0.0;

        $display("FUNC_SUMMARY pass=%0d fail=%0d total=%0d", pass_cnt, fail_cnt, total);
        $display("FUNC_SCORE: %0.6f", func_score);  // <- gateway parses this

        $finish;
    end
endmodule

RTL/src/RV64I_Core/RISCV_DV/verilator/adder_4bit.vcd
$version Generated by VerilatedVcd $end
$timescale 1ps $end
 $scope module tb_adder_4bit $end
  $var wire 4 # a [3:0] $end
  $var wire 4 $ b [3:0] $end
  $var wire 1 % cin $end
  $var wire 4 B sum [3:0] $end
  $var wire 1 C cout $end
  $var wire 32 & pass_cnt [31:0] $end
  $var wire 32 ' fail_cnt [31:0] $end
  $var wire 32 ( total [31:0] $end
  $var wire 32 ) i [31:0] $end
  $var wire 32 * num_tests [31:0] $end
  $var wire 32 + max_fail_logs [31:0] $end
  $var wire 32 , fail_logs [31:0] $end
  $var wire 32 - seed [31:0] $end
  $var wire 5 . exp [4:0] $end
  $var wire 4 / exp_sum [3:0] $end
  $var wire 1 0 exp_cout $end
  $var real 64 1 func_score $end
  $scope module uut $end
   $var wire 4 # a [3:0] $end
   $var wire 4 $ b [3:0] $end
   $var wire 1 % cin $end
   $var wire 4 B sum [3:0] $end
   $var wire 1 C cout $end
   $var wire 1 L c1 $end
   $var wire 1 M c2 $end
   $var wire 1 N c3 $end
   $scope module fa0 $end
    $var wire 1 3 a $end
    $var wire 1 4 b $end
    $var wire 1 % cin $end
    $var wire 1 D sum $end
    $var wire 1 L cout $end
    $var wire 1 O s1 $end
    $var wire 1 5 c_out1 $end
    $var wire 1 E c_out2 $end
    $scope module ha1 $end
     $var wire 1 3 a $end
     $var wire 1 4 b $end
     $var wire 1 O sum $end
     $var wire 1 5 cout $end
    $upscope $end
    $scope module ha2 $end
     $var wire 1 O a $end
     $var wire 1 % b $end
     $var wire 1 D sum $end
     $var wire 1 E cout $end
    $upscope $end
   $upscope $end
   $scope module fa1 $end
    $var wire 1 6 a $end
    $var wire 1 7 b $end
    $var wire 1 L cin $end
    $var wire 1 F sum $end
    $var wire 1 M cout $end
    $var wire 1 8 s1 $end
    $var wire 1 9 c_out1 $end
    $var wire 1 G c_out2 $end
    $scope module ha1 $end
     $var wire 1 6 a $end
     $var wire 1 7 b $end
     $var wire 1 8 sum $end
     $var wire 1 9 cout $end
    $upscope $end
    $scope module ha2 $end
     $var wire 1 8 a $end
     $var wire 1 L b $end
     $var wire 1 F sum $end
     $var wire 1 G cout $end
    $upscope $end
   $upscope $end
   $scope module fa2 $end
    $var wire 1 : a $end
    $var wire 1 ; b $end
    $var wire 1 M cin $end
    $var wire 1 H sum $end
    $var wire 1 N cout $end
    $var wire 1 < s1 $end
    $var wire 1 = c_out1 $end
    $var wire 1 I c_out2 $end
    $scope module ha1 $end
     $var wire 1 : a $end
     $var wire 1 ; b $end
     $var wire 1 < sum $end
     $var wire 1 = cout $end
    $upscope $end
    $scope module ha2 $end
     $var wire 1 < a $end
     $var wire 1 M b $end
     $var wire 1 H sum $end
     $var wire 1 I cout $end
    $upscope $end
   $upscope $end
   $scope module fa3 $end
    $var wire 1 > a $end
    $var wire 1 ? b $end
    $var wire 1 N cin $end
    $var wire 1 J sum $end
    $var wire 1 C cout $end
    $var wire 1 @ s1 $end
    $var wire 1 A c_out1 $end
    $var wire 1 K c_out2 $end
    $scope module ha1 $end
     $var wire 1 > a $end
     $var wire 1 ? b $end
     $var wire 1 @ sum $end
     $var wire 1 A cout $end
    $upscope $end
    $scope module ha2 $end
     $var wire 1 @ a $end
     $var wire 1 N b $end
     $var wire 1 J sum $end
     $var wire 1 K cout $end
    $upscope $end
   $upscope $end
  $upscope $end
 $upscope $end
$enddefinitions $end


#0
b0000 #
b0000 $
0%
b00000000000000000000000000000000 &
b00000000000000000000000000000000 '
b00000000000000000000000000000000 (
b00000000000000000000000000000000 )
b00000000000000000000001111101000 *
b00000000000000000000000000010100 +
b00000000000000000000000000000000 ,
b00000000000000000000000000000001 -
b00000 .
b0000 /
00
r0 1
03
04
05
06
07
08
09
0:
0;
0<
0=
0>
0?
0@
0A
b0000 B
0C
0D
0E
0F
0G
0H
0I
0J
0K
0L
0M
0N
0O
#1000
b1111 #
b1111 $
1%
b11111111111111111111111111110000 -
13
14
15
16
17
19
1:
1;
1=
1>
1?
1A
b1111 B
1C
1D
1F
1H
1J
1L
1M
1N
#2000
b00000000000000000000000000000001 &
b00000000000000000000000000000001 (
b00000000000000000000000000000001 )
b11111111111111111111111110000000 -
b11111 .
b1111 /
10
#3000
b00000000000000000000000000000010 &
b00000000000000000000000000000010 (
b00000000000000000000000000000010 )
b11111111111111111111110000000000 -
#4000
b1110 #
b1100 $
0%
b00000000000000000000000000000011 &
b00000000000000000000000000000011 (
b00000000000000000000000000000011 )
b11111111111111111110000000000000 -
03
04
05
07
18
09
b1010 B
0D
0H
0L
0M
#5000
b0000 #
b0000 $
b00000000000000000000000000000100 &
b00000000000000000000000000000100 (
b00000000000000000000000000000100 )
b11111111111111110000000000000000 -
b11010 .
b1010 /
06
08
0:
0;
0=
0>
0?
0A
b0000 B
0C
0F
0J
0N
#6000
b00000000000000000000000000000101 &
b00000000000000000000000000000101 (
b00000000000000000000000000000101 )
b11111111111110000000000000000000 -
b00000 .
b0000 /
00
#7000
b00000000000000000000000000000110 &
b00000000000000000000000000000110 (
b00000000000000000000000000000110 )
b11111111110000000000000000000000 -
#8000
b1111 $
1%
b00000000000000000000000000000111 &
b00000000000000000000000000000111 (
b00000000000000000000000000000111 )
b00000001111111111111111111111100 -
14
17
18
1;
1<
1?
1@
1C
1E
1G
1I
1K
1L
1M
1N
1O
#9000
b1111 #
b00000000000000000000000000001000 &
b00000000000000000000000000001000 (
b00000000000000000000000000001000 )
b00001111111111111111111111100000 -
b10000 .
10
13
15
16
08
19
1:
0<
1=
1>
0@
1A
b1111 B
1D
0E
1F
0G
1H
0I
1J
0K
0O
#10000
b00000000000000000000000000001001 &
b00000000000000000000000000001001 (
b00000000000000000000000000001001 )
b01111111111111111111111100000000 -
b11111 .
b1111 /
#11000
0%
b00000000000000000000000000001010 &
b00000000000000000000000000001010 (
b00000000000000000000000000001010 )
b11111111111111111111100000000000 -
b1110 B
0D
#12000
b1100 #
b1000 $
b00000000000000000000000000001011 &
b00000000000000000000000000001011 (
b00000000000000000000000000001011 )
b11111111111111111100000000000000 -
b11110 .
b1110 /
03
04
05
06
07
09
0;
1<
0=
b0100 B
0F
0J
0L
0M
0N
#13000
b0000 #
b0000 $
b00000000000000000000000000001100 &
b00000000000000000000000000001100 (
b00000000000000000000000000001100 )
b11111111111111100000000000000000 -
b10100 .
b0100 /
0:
0<
0>
0?
0A
b0000 B
0C
0H
#14000
b00000000000000000000000000001101 &
b00000000000000000000000000001101 (
b00000000000000000000000000001101 )
b11111111111100000000000000000000 -
b00000 .
b0000 /
00
#15000
b00000000000000000000000000001110 &
b00000000000000000000000000001110 (
b00000000000000000000000000001110 )
b11111111100000000000000000000000 -
#16000
b1111 #
b1111 $
1%
b00000000000000000000000000001111 &
b00000000000000000000000000001111 (
b00000000000000000000000000001111 )
b00000011111111111111111111111000 -
13
14
15
16
17
19
1:
1;
1=
1>
1?
1A
b1111 B
1C
1D
1F
1H
1J
1L
1M
1N
#17000
b00000000000000000000000000010000 &
b00000000000000000000000000010000 (
b00000000000000000000000000010000 )
b00011111111111111111111111000000 -
b11111 .
b1111 /
10
#18000
b00000000000000000000000000010001 &
b00000000000000000000000000010001 (
b00000000000000000000000000010001 )
b11111111111111111111111000000000 -
#19000
b1110 $
0%
b00000000000000000000000000010010 &
b00000000000000000000000000010010 (
b00000000000000000000000000010010 )
b11111111111111111111000000000000 -
04
05
b1101 B
0F
0L
1O
#20000
b1000 #
b0000 $
b00000000000000000000000000010011 &
b00000000000000000000000000010011 (
b00000000000000000000000000010011 )
b11111111111111111000000000000000 -
b11101 .
b1101 /
03
06
07
09
0:
0;
0=
0?
1@
0A
b1000 B
0C
0D
0H
0M
0N
0O
#21000
b0000 #
b00000000000000000000000000010100 &
b00000000000000000000000000010100 (
b00000000000000000000000000010100 )
b11111111111111000000000000000000 -
b01000 .
b1000 /
00
0>
0@
b0000 B
0J
#22000
b00000000000000000000000000010101 &
b00000000000000000000000000010101 (
b00000000000000000000000000010101 )
b11111111111000000000000000000000 -
b00000 .
b0000 /
#23000
1%
b00000000000000000000000000010110 &
b00000000000000000000000000010110 (
b00000000000000000000000000010110 )
b00000000111111111111111111111110 -
b0001 B
1D
#24000
b1111 #
b1111 $
b00000000000000000000000000010111 &
b00000000000000000000000000010111 (
b00000000000000000000000000010111 )
b00000111111111111111111111110000 -
b00001 .
b0001 /
13
14
15
16
17
19
1:
1;
1=
1>
1?
1A
b1111 B
1C
1F
1H
1J
1L
1M
1N
#25000
b00000000000000000000000000011000 &
b00000000000000000000000000011000 (
b00000000000000000000000000011000 )
b00111111111111111111111110000000 -
b11111 .
b1111 /
10
#26000
b00000000000000000000000000011001 &
b00000000000000000000000000011001 (
b00000000000000000000000000011001 )
b11111111111111111111110000000000 -
#27000
b1110 #
b1100 $
0%
b00000000000000000000000000011010 &
b00000000000000000000000000011010 (
b00000000000000000000000000011010 )
b11111111111111111110000000000000 -
03
04
05
07
18
09
b1010 B
0D
0H
0L
0M
#28000
b0000 #
b0000 $
b00000000000000000000000000011011 &
b00000000000000000000000000011011 (
b00000000000000000000000000011011 )
b11111111111111110000000000000000 -
b11010 .
b1010 /
06
08
0:
0;
0=
0>
0?
0A
b0000 B
0C
0F
0J
0N
#29000
b00000000000000000000000000011100 &
b00000000000000000000000000011100 (
b00000000000000000000000000011100 )
b11111111111110000000000000000000 -
b00000 .
b0000 /
00
#30000
b00000000000000000000000000011101 &
b00000000000000000000000000011101 (
b00000000000000000000000000011101 )
b11111111110000000000000000000000 -
#31000
b1111 $
1%
b00000000000000000000000000011110 &
b00000000000000000000000000011110 (
b00000000000000000000000000011110 )
b00000001111111111111111111111100 -
14
17
18
1;
1<
1?
1@
1C
1E
1G
1I
1K
1L
1M
1N
1O
#32000
b1111 #
b00000000000000000000000000011111 &
b00000000000000000000000000011111 (
b00000000000000000000000000011111 )
b00001111111111111111111111100000 -
b10000 .
10
13
15
16
08
19
1:
0<
1=
1>
0@
1A
b1111 B
1D
0E
1F
0G
1H
0I
1J
0K
0O
#33000
b00000000000000000000000000100000 &
b00000000000000000000000000100000 (
b00000000000000000000000000100000 )
b01111111111111111111111100000000 -
b11111 .
b1111 /
#34000
0%
b00000000000000000000000000100001 &
b00000000000000000000000000100001 (
b00000000000000000000000000100001 )
b11111111111111111111100000000000 -
b1110 B
0D
#35000
b1100 #
b1000 $
b00000000000000000000000000100010 &
b00000000000000000000000000100010 (
b00000000000000000000000000100010 )
b11111111111111111100000000000000 -
b11110 .
b1110 /
03
04
05
06
07
09
0;
1<
0=
b0100 B
0F
0J
0L
0M
0N
#36000
b0000 #
b0000 $
b00000000000000000000000000100011 &
b00000000000000000000000000100011 (
b00000000000000000000000000100011 )
b11111111111111100000000000000000 -
b10100 .
b0100 /
0:
0<
0>
0?
0A
b0000 B
0C
0H
#37000
b00000000000000000000000000100100 &
b00000000000000000000000000100100 (
b00000000000000000000000000100100 )
b11111111111100000000000000000000 -
b00000 .
b0000 /
00
#38000
b00000000000000000000000000100101 &
b00000000000000000000000000100101 (
b00000000000000000000000000100101 )
b11111111100000000000000000000000 -
#39000
b1111 #
b1111 $
1%
b00000000000000000000000000100110 &
b00000000000000000000000000100110 (
b00000000000000000000000000100110 )
b00000011111111111111111111111000 -
13
14
15
16
17
19
1:
1;
1=
1>
1?
1A
b1111 B
1C
1D
1F
1H
1J
1L
1M
1N
#40000
b00000000000000000000000000100111 &
b00000000000000000000000000100111 (
b00000000000000000000000000100111 )
b00011111111111111111111111000000 -
b11111 .
b1111 /
10
#41000
b00000000000000000000000000101000 &
b00000000000000000000000000101000 (
b00000000000000000000000000101000 )
b11111111111111111111111000000000 -
#42000
b1110 $
0%
b00000000000000000000000000101001 &
b00000000000000000000000000101001 (
b00000000000000000000000000101001 )
b11111111111111111111000000000000 -
04
05
b1101 B
0F
0L
1O
#43000
b1000 #
b0000 $
b00000000000000000000000000101010 &
b00000000000000000000000000101010 (
b00000000000000000000000000101010 )
b11111111111111111000000000000000 -
b11101 .
b1101 /
03
06
07
09
0:
0;
0=
0?
1@
0A
b1000 B
0C
0D
0H
0M
0N
0O
#44000
b0000 #
b00000000000000000000000000101011 &
b00000000000000000000000000101011 (
b00000000000000000000000000101011 )
b11111111111111000000000000000000 -
b01000 .
b1000 /
00
0>
0@
b0000 B
0J
#45000
b00000000000000000000000000101100 &
b00000000000000000000000000101100 (
b00000000000000000000000000101100 )
b11111111111000000000000000000000 -
b00000 .
b0000 /
#46000
1%
b00000000000000000000000000101101 &
b00000000000000000000000000101101 (
b00000000000000000000000000101101 )
b00000000111111111111111111111110 -
b0001 B
1D
#47000
b1111 #
b1111 $
b00000000000000000000000000101110 &
b00000000000000000000000000101110 (
b00000000000000000000000000101110 )
b00000111111111111111111111110000 -
b00001 .
b0001 /
13
14
15
16
17
19
1:
1;
1=
1>
1?
1A
b1111 B
1C
1F
1H
1J
1L
1M
1N
#48000
b00000000000000000000000000101111 &
b00000000000000000000000000101111 (
b00000000000000000000000000101111 )
b00111111111111111111111110000000 -
b11111 .
b1111 /
10
#49000
b00000000000000000000000000110000 &
b00000000000000000000000000110000 (
b00000000000000000000000000110000 )
b11111111111111111111110000000000 -
#50000
b1110 #
b1100 $
0%
b00000000000000000000000000110001 &
b00000000000000000000000000110001 (
b00000000000000000000000000110001 )
b11111111111111111110000000000000 -
03
04
05
07
18
09
b1010 B
0D
0H
0L
0M
#51000
b0000 #
b0000 $
b00000000000000000000000000110010 &
b00000000000000000000000000110010 (
b00000000000000000000000000110010 )
b11111111111111110000000000000000 -
b11010 .
b1010 /
06
08
0:
0;
0=
0>
0?
0A
b0000 B
0C
0F
0J
0N
#52000
b00000000000000000000000000110011 &
b00000000000000000000000000110011 (
b00000000000000000000000000110011 )
b11111111111110000000000000000000 -
b00000 .
b0000 /
00
#53000
b00000000000000000000000000110100 &
b00000000000000000000000000110100 (
b00000000000000000000000000110100 )
b11111111110000000000000000000000 -
#54000
b1111 $
1%
b00000000000000000000000000110101 &
b00000000000000000000000000110101 (
b00000000000000000000000000110101 )
b00000001111111111111111111111100 -
14
17
18
1;
1<
1?
1@
1C
1E
1G
1I
1K
1L
1M
1N
1O
#55000
b1111 #
b00000000000000000000000000110110 &
b00000000000000000000000000110110 (
b00000000000000000000000000110110 )
b00001111111111111111111111100000 -
b10000 .
10
13
15
16
08
19
1:
0<
1=
1>
0@
1A
b1111 B
1D
0E
1F
0G
1H
0I
1J
0K
0O
#56000
b00000000000000000000000000110111 &
b00000000000000000000000000110111 (
b00000000000000000000000000110111 )
b01111111111111111111111100000000 -
b11111 .
b1111 /
#57000
0%
b00000000000000000000000000111000 &
b00000000000000000000000000111000 (
b00000000000000000000000000111000 )
b11111111111111111111100000000000 -
b1110 B
0D
#58000
b1100 #
b1000 $
b00000000000000000000000000111001 &
b00000000000000000000000000111001 (
b00000000000000000000000000111001 )
b11111111111111111100000000000000 -
b11110 .
b1110 /
03
04
05
06
07
09
0;
1<
0=
b0100 B
0F
0J
0L
0M
0N
#59000
b0000 #
b0000 $
b00000000000000000000000000111010 &
b00000000000000000000000000111010 (
b00000000000000000000000000111010 )
b11111111111111100000000000000000 -
b10100 .
b0100 /
0:
0<
0>
0?
0A
b0000 B
0C
0H
#60000
b00000000000000000000000000111011 &
b00000000000000000000000000111011 (
b00000000000000000000000000111011 )
b11111111111100000000000000000000 -
b00000 .
b0000 /
00
#61000
b00000000000000000000000000111100 &
b00000000000000000000000000111100 (
b00000000000000000000000000111100 )
b11111111100000000000000000000000 -
#62000
b1111 #
b1111 $
1%
b00000000000000000000000000111101 &
b00000000000000000000000000111101 (
b00000000000000000000000000111101 )
b00000011111111111111111111111000 -
13
14
15
16
17
19
1:
1;
1=
1>
1?
1A
b1111 B
1C
1D
1F
1H
1J
1L
1M
1N
#63000
b00000000000000000000000000111110 &
b00000000000000000000000000111110 (
b00000000000000000000000000111110 )
b00011111111111111111111111000000 -
b11111 .
b1111 /
10
#64000
b00000000000000000000000000111111 &
b00000000000000000000000000111111 (
b00000000000000000000000000111111 )
b11111111111111111111111000000000 -
#65000
b1110 $
0%
b00000000000000000000000001000000 &
b00000000000000000000000001000000 (
b00000000000000000000000001000000 )
b11111111111111111111000000000000 -
04
05
b1101 B
0F
0L
1O
#66000
b1000 #
b0000 $
b00000000000000000000000001000001 &
b00000000000000000000000001000001 (
b00000000000000000000000001000001 )
b11111111111111111000000000000000 -
b11101 .
b1101 /
03
06
07
09
0:
0;
0=
0?
1@
0A
b1000 B
0C
0D
0H
0M
0N
0O
#67000
b0000 #
b00000000000000000000000001000010 &
b00000000000000000000000001000010 (
b00000000000000000000000001000010 )
b11111111111111000000000000000000 -
b01000 .
b1000 /
00
0>
0@
b0000 B
0J
#68000
b00000000000000000000000001000011 &
b00000000000000000000000001000011 (
b00000000000000000000000001000011 )
b11111111111000000000000000000000 -
b00000 .
b0000 /
#69000
1%
b00000000000000000000000001000100 &
b00000000000000000000000001000100 (
b00000000000000000000000001000100 )
b00000000111111111111111111111110 -
b0001 B
1D
#70000
b1111 #
b1111 $
b00000000000000000000000001000101 &
b00000000000000000000000001000101 (
b00000000000000000000000001000101 )
b00000111111111111111111111110000 -
b00001 .
b0001 /
13
14
15
16
17
19
1:
1;
1=
1>
1?
1A
b1111 B
1C
1F
1H
1J
1L
1M
1N
#71000
b00000000000000000000000001000110 &
b00000000000000000000000001000110 (
b00000000000000000000000001000110 )
b00111111111111111111111110000000 -
b11111 .
b1111 /
10
#72000
b00000000000000000000000001000111 &
b00000000000000000000000001000111 (
b00000000000000000000000001000111 )
b11111111111111111111110000000000 -
#73000
b1110 #
b1100 $
0%
b00000000000000000000000001001000 &
b00000000000000000000000001001000 (
b00000000000000000000000001001000 )
b11111111111111111110000000000000 -
03
04
05
07
18
09
b1010 B
0D
0H
0L
0M
#74000
b0000 #
b0000 $
b00000000000000000000000001001001 &
b00000000000000000000000001001001 (
b00000000000000000000000001001001 )
b11111111111111110000000000000000 -
b11010 .
b1010 /
06
08
0:
0;
0=
0>
0?
0A
b0000 B
0C
0F
0J
0N
#75000
b00000000000000000000000001001010 &
b00000000000000000000000001001010 (
b00000000000000000000000001001010 )
b11111111111110000000000000000000 -
b00000 .
b0000 /
00
#76000
b00000000000000000000000001001011 &
b00000000000000000000000001001011 (
b00000000000000000000000001001011 )
b11111111110000000000000000000000 -
#77000
b1111 $
1%
b00000000000000000000000001001100 &
b00000000000000000000000001001100 (
b00000000000000000000000001001100 )
b00000001111111111111111111111100 -
14
17
18
1;
1<
1?
1@
1C
1E
1G
1I
1K
1L
1M
1N
1O
#78000
b1111 #
b00000000000000000000000001001101 &
b00000000000000000000000001001101 (
b00000000000000000000000001001101 )
b00001111111111111111111111100000 -
b10000 .
10
13
15
16
08
19
1:
0<
1=
1>
0@
1A
b1111 B
1D
0E
1F
0G
1H
0I
1J
0K
0O
#79000
b00000000000000000000000001001110 &
b00000000000000000000000001001110 (
b00000000000000000000000001001110 )
b01111111111111111111111100000000 -
b11111 .
b1111 /
#80000
0%
b00000000000000000000000001001111 &
b00000000000000000000000001001111 (
b00000000000000000000000001001111 )
b11111111111111111111100000000000 -
b1110 B
0D
#81000
b1100 #
b1000 $
b00000000000000000000000001010000 &
b00000000000000000000000001010000 (
b00000000000000000000000001010000 )
b11111111111111111100000000000000 -
b11110 .
b1110 /
03
04
05
06
07
09
0;
1<
0=
b0100 B
0F
0J
0L
0M
0N
#82000
b0000 #
b0000 $
b00000000000000000000000001010001 &
b00000000000000000000000001010001 (
b00000000000000000000000001010001 )
b11111111111111100000000000000000 -
b10100 .
b0100 /
0:
0<
0>
0?
0A
b0000 B
0C
0H
#83000
b00000000000000000000000001010010 &
b00000000000000000000000001010010 (
b00000000000000000000000001010010 )
b11111111111100000000000000000000 -
b00000 .
b0000 /
00
#84000
b00000000000000000000000001010011 &
b00000000000000000000000001010011 (
b00000000000000000000000001010011 )
b11111111100000000000000000000000 -
#85000
b1111 #
b1111 $
1%
b00000000000000000000000001010100 &
b00000000000000000000000001010100 (
b00000000000000000000000001010100 )
b00000011111111111111111111111000 -
13
14
15
16
17
19
1:
1;
1=
1>
1?
1A
b1111 B
1C
1D
1F
1H
1J
1L
1M
1N
#86000
b00000000000000000000000001010101 &
b00000000000000000000000001010101 (
b00000000000000000000000001010101 )
b00011111111111111111111111000000 -
b11111 .
b1111 /
10
#87000
b00000000000000000000000001010110 &
b00000000000000000000000001010110 (
b00000000000000000000000001010110 )
b11111111111111111111111000000000 -
#88000
b1110 $
0%
b00000000000000000000000001010111 &
b00000000000000000000000001010111 (
b00000000000000000000000001010111 )
b11111111111111111111000000000000 -
04
05
b1101 B
0F
0L
1O
#89000
b1000 #
b0000 $
b00000000000000000000000001011000 &
b00000000000000000000000001011000 (
b00000000000000000000000001011000 )
b11111111111111111000000000000000 -
b11101 .
b1101 /
03
06
07
09
0:
0;
0=
0?
1@
0A
b1000 B
0C
0D
0H
0M
0N
0O
#90000
b0000 #
b00000000000000000000000001011001 &
b00000000000000000000000001011001 (
b00000000000000000000000001011001 )
b11111111111111000000000000000000 -
b01000 .
b1000 /
00
0>
0@
b0000 B
0J
#91000
b00000000000000000000000001011010 &
b00000000000000000000000001011010 (
b00000000000000000000000001011010 )
b11111111111000000000000000000000 -
b00000 .
b0000 /
#92000
1%
b00000000000000000000000001011011 &
b00000000000000000000000001011011 (
b00000000000000000000000001011011 )
b00000000111111111111111111111110 -
b0001 B
1D
#93000
b1111 #
b1111 $
b00000000000000000000000001011100 &
b00000000000000000000000001011100 (
b00000000000000000000000001011100 )
b00000111111111111111111111110000 -
b00001 .
b0001 /
13
14
15
16
17
19
1:
1;
1=
1>
1?
1A
b1111 B
1C
1F
1H
1J
1L
1M
1N
#94000
b00000000000000000000000001011101 &
b00000000000000000000000001011101 (
b00000000000000000000000001011101 )
b00111111111111111111111110000000 -
b11111 .
b1111 /
10
#95000
b00000000000000000000000001011110 &
b00000000000000000000000001011110 (
b00000000000000000000000001011110 )
b11111111111111111111110000000000 -
#96000
b1110 #
b1100 $
0%
b00000000000000000000000001011111 &
b00000000000000000000000001011111 (
b00000000000000000000000001011111 )
b11111111111111111110000000000000 -
03
04
05
07
18
09
b1010 B
0D
0H
0L
0M
#97000
b0000 #
b0000 $
b00000000000000000000000001100000 &
b00000000000000000000000001100000 (
b00000000000000000000000001100000 )
b11111111111111110000000000000000 -
b11010 .
b1010 /
06
08
0:
0;
0=
0>
0?
0A
b0000 B
0C
0F
0J
0N
#98000
b00000000000000000000000001100001 &
b00000000000000000000000001100001 (
b00000000000000000000000001100001 )
b11111111111110000000000000000000 -
b00000 .
b0000 /
00
#99000
b00000000000000000000000001100010 &
b00000000000000000000000001100010 (
b00000000000000000000000001100010 )
b11111111110000000000000000000000 -
#100000
b1111 $
1%
b00000000000000000000000001100011 &
b00000000000000000000000001100011 (
b00000000000000000000000001100011 )
b00000001111111111111111111111100 -
14
17
18
1;
1<
1?
1@
1C
1E
1G
1I
1K
1L
1M
1N
1O
#101000
b1111 #
b00000000000000000000000001100100 &
b00000000000000000000000001100100 (
b00000000000000000000000001100100 )
b00001111111111111111111111100000 -
b10000 .
10
13
15
16
08
19
1:
0<
1=
1>
0@
1A
b1111 B
1D
0E
1F
0G
1H
0I
1J
0K
0O
#102000
b00000000000000000000000001100101 &
b00000000000000000000000001100101 (
b00000000000000000000000001100101 )
b01111111111111111111111100000000 -
b11111 .
b1111 /
#103000
0%
b00000000000000000000000001100110 &
b00000000000000000000000001100110 (
b00000000000000000000000001100110 )
b11111111111111111111100000000000 -
b1110 B
0D
#104000
b1100 #
b1000 $
b00000000000000000000000001100111 &
b00000000000000000000000001100111 (
b00000000000000000000000001100111 )
b11111111111111111100000000000000 -
b11110 .
b1110 /
03
04
05
06
07
09
0;
1<
0=
b0100 B
0F
0J
0L
0M
0N
#105000
b0000 #
b0000 $
b00000000000000000000000001101000 &
b00000000000000000000000001101000 (
b00000000000000000000000001101000 )
b11111111111111100000000000000000 -
b10100 .
b0100 /
0:
0<
0>
0?
0A
b0000 B
0C
0H
#106000
b00000000000000000000000001101001 &
b00000000000000000000000001101001 (
b00000000000000000000000001101001 )
b11111111111100000000000000000000 -
b00000 .
b0000 /
00
#107000
b00000000000000000000000001101010 &
b00000000000000000000000001101010 (
b00000000000000000000000001101010 )
b11111111100000000000000000000000 -
#108000
b1111 #
b1111 $
1%
b00000000000000000000000001101011 &
b00000000000000000000000001101011 (
b00000000000000000000000001101011 )
b00000011111111111111111111111000 -
13
14
15
16
17
19
1:
1;
1=
1>
1?
1A
b1111 B
1C
1D
1F
1H
1J
1L
1M
1N
#109000
b00000000000000000000000001101100 &
b00000000000000000000000001101100 (
b00000000000000000000000001101100 )
b00011111111111111111111111000000 -
b11111 .
b1111 /
10
#110000
b00000000000000000000000001101101 &
b00000000000000000000000001101101 (
b00000000000000000000000001101101 )
b11111111111111111111111000000000 -
#111000
b1110 $
0%
b00000000000000000000000001101110 &
b00000000000000000000000001101110 (
b00000000000000000000000001101110 )
b11111111111111111111000000000000 -
04
05
b1101 B
0F
0L
1O
#112000
b1000 #
b0000 $
b00000000000000000000000001101111 &
b00000000000000000000000001101111 (
b00000000000000000000000001101111 )
b11111111111111111000000000000000 -
b11101 .
b1101 /
03
06
07
09
0:
0;
0=
0?
1@
0A
b1000 B
0C
0D
0H
0M
0N
0O
